{
  "id": "https://JuanDVillarraga.github.io/prototipo/iiif/aqui_arg04/manifest/image-0.json",
  "items": [],
  "type": "Annotation",
  "@context": "http://www.w3.org/ns/anno.jsonld",
  "motivation": "painting",
  "target": "https://JuanDVillarraga.github.io/prototipo/iiif/aqui_arg04/manifest/canvas-0.json",
  "body": {
    "id": "https://JuanDVillarraga.github.io/prototipo/iiif/aqui_arg04/0/full/max/0/default.jpg",
    "type": "Image",
    "format": "image/jpeg",
    "height": 360,
    "width": 450
  }
}